setup.cfg
setup.py
class_file_Nikolay/_init_.py
class_file_Nikolay/class_file.py
class_file_Nikolay.egg-info/PKG-INFO
class_file_Nikolay.egg-info/SOURCES.txt
class_file_Nikolay.egg-info/dependency_links.txt
class_file_Nikolay.egg-info/not-zip-safe
class_file_Nikolay.egg-info/top_level.txt