Metadata-Version: 2.1
Name: class-file-Nikolay
Version: 0.4
Summary: удобный класс дял работы с файлом
Author-email: nikolajh913@gmail.com
